mn/__init__.py
mn/perceptron.py
perceptron_itsguptaaman-0.0.3.dist-info/LICENCE
perceptron_itsguptaaman-0.0.3.dist-info/METADATA
perceptron_itsguptaaman-0.0.3.dist-info/WHEEL
perceptron_itsguptaaman-0.0.3.dist-info/top_level.txt
perceptron_itsguptaaman-0.0.3.dist-info/RECORD
