Metadata-Version: 2.1
Name: perceptron-itsguptaaman
Version: 0.0.3
Summary: A small package for perceptron
Home-page: https://github.com/itsguptaaman/Perceptron_package
Author: itsguptaaman
Author-email: itsamangupta420@gmail.com
Project-URL: Bug Tracker, https://github.com/itsguptaaman/Perceptron_package/issues
Classifier: Programming Language :: Python :: 3
Classifier: License :: OSI Approved :: MIT License
Classifier: Operating System :: OS Independent
Requires-Python: >=3.6
License-File: LICENCE
Requires-Dist: numpy (==1.21.4)
Requires-Dist: pandas (==1.3.4)
Requires-Dist: joblib (==1.1.0)
